{
    "UniqueID": "125b9691-49cb-4fe0-8f1d-cec8c227ca2b",
    "ID": "D3041.011a",
    "Description": "Costing based upon 1000 ft segments of duct",
    "BasicUnit": "Each",
    "Name": "HVAC Galvanized Sheet Metal Ducting less than 6 sq. ft in cross sectional area, SDC A or B",
    "Author": "Not Given",
    "Correlation": 0,
    "Directional": false,
    "EDPType": {
        "Dimension": "NumLevelsPlusOne",
        "TypeName": "Acceleration",
        "DefaultUnits": "g",
        "UserDefined": false
    },
    "Ratings": {
        "DataQuality": "Marginal",
        "DataRelevance": "Superior",
        "Documentation": "Marginal",
        "Rationality": "Marginal"
    },
    "Official": true,
    "DateCreated": "2012-10-12T16:48:27.5175683-07:00",
    "Approved": true,
    "Incomplete": false,
    "Notes": "None",
    "UseEDPValueOfFloorAbove": true,
    "DamageStates": {
        "DSGroupType": "Sequential",
        "DamageState": [
            {
                "Name": null,
                "Description": "Individual supports fail and duct sags - 1 failed support per 1000 feet of ducting",
                "DamageImageName": null,
                "ConsequenceGroup": {
                    "RepairMeasures": "Replace failed supports and repair ducting in vicinity of failed supports.",
                    "TagState": 0,
                    "UseCasualty": false,
                    "LongLeadFlag": false,
                    "AffectedFloorArea": null,
                    "AffectedDeathRate": 0,
                    "AffectedInjuryRate": 0,
                    "AffectedDeathRateBeta": 0,
                    "AffectedInjuryRateBeta": 0,
                    "RedTagMedian": 0,
                    "RedTagBeta": 0,
                    "CostConsequence": {
                        "LowerQuantity": 250,
                        "MaxAmount": 1300,
                        "UpperQuantity": 500,
                        "MinAmount": 390,
                        "Uncertainty": 0.3674,
                        "CurveType": "LogNormal"
                    },
                    "TimeConsequence": {
                        "LowerQuantity": 250,
                        "MaxAmount": 3.6059,
                        "UpperQuantity": 500,
                        "MinAmount": 1.3577,
                        "Uncertainty": 0.3902,
                        "CurveType": "Normal"
                    }
                },
                "Median": 1.5,
                "Beta": 0.4
            },
            {
                "Name": null,
                "Description": "Several adjacent supports fail and sections of ducting fall - 60 feet of ducting fail and fall per 1000 foot of ducting",
                "DamageImageName": null,
                "ConsequenceGroup": {
                    "RepairMeasures": "Replace sections of failed ducting and supports.",
                    "TagState": 0,
                    "UseCasualty": true,
                    "LongLeadFlag": false,
                    "AffectedFloorArea": {
                        "Area": {
                            "Unit": "Square Foot",
                            "Value": 15
                        }
                    },
                    "AffectedDeathRate": 0,
                    "AffectedInjuryRate": 0.05,
                    "AffectedDeathRateBeta": 0,
                    "AffectedInjuryRateBeta": 0.5,
                    "RedTagMedian": 0,
                    "RedTagBeta": 0,
                    "CostConsequence": {
                        "LowerQuantity": 250,
                        "MaxAmount": 12700,
                        "UpperQuantity": 500,
                        "MinAmount": 3810,
                        "Uncertainty": 0.1002,
                        "CurveType": "LogNormal"
                    },
                    "TimeConsequence": {
                        "LowerQuantity": 250,
                        "MaxAmount": 31.6882,
                        "UpperQuantity": 500,
                        "MinAmount": 9.7247,
                        "Uncertainty": 0.0975,
                        "CurveType": "Normal"
                    }
                },
                "Median": 2.25,
                "Beta": 0.4
            }
        ]
    }
}